easyjson/__init__.py
easierjson-0.0.2.dist-info/METADATA
easierjson-0.0.2.dist-info/WHEEL
easierjson-0.0.2.dist-info/top_level.txt
easierjson-0.0.2.dist-info/RECORD
