Metadata-Version: 2.1
Name: easierjson
Version: 0.0.2
Summary: A way to use JSON efficiently and properly
Home-page: http://github.com/Ehnryu/easyjson
Author: Ehnryu/Sakurai07
Author-email: blzzardst0rm@gmail.com
License: MIT
Keywords: easjson,fast,json
Platform: UNKNOWN
